chemcurry/__init__.py
chemcurry/molecule.py
chemcurry/steps/__init__.py
chemcurry/steps/add_3d.py
chemcurry/steps/add_hydrogen.py
chemcurry/steps/base.py
chemcurry/steps/boron.py
chemcurry/steps/charge.py
chemcurry/steps/inorganic.py
chemcurry/steps/mixture.py
chemcurry/steps/mw.py
chemcurry/steps/remove_hydrogen.py
chemcurry/steps/sanitize.py
chemcurry/steps/stereochem.py
chemcurry/workflow.py
chemcurry-0.1.2.dist-info/METADATA
chemcurry-0.1.2.dist-info/WHEEL
chemcurry-0.1.2.dist-info/RECORD
