Metadata-Version: 2.1
Name: chemcurry
Version: 0.1.2
Summary: 
Author: James Wellnitz
Author-email: wellnitz.james@gmail.com
Requires-Python: >=3.11,<4.0
Classifier: Natural Language :: English
Classifier: Operating System :: OS Independent
Classifier: Programming Language :: Python :: 3
Classifier: Programming Language :: Python :: 3.11
Classifier: Programming Language :: Python :: 3.12
Classifier: Programming Language :: Python :: 3.13
Requires-Dist: func-timeout (>=4.3.5,<5.0.0)
Requires-Dist: numpy (>=2.2.0,<3.0.0)
Requires-Dist: pandas (>=2.2.3,<3.0.0)
Requires-Dist: rdkit (>=2024.3.6,<2025.0.0)
